swh/journal/__init__.py
swh/journal/client.py
swh/journal/py.typed
swh/journal/pytest_plugin.py
swh/journal/serializers.py
swh/journal/tests/__init__.py
swh/journal/tests/log4j.properties
swh/journal/tests/test_client.py
swh/journal/tests/test_inmemory.py
swh/journal/tests/test_kafka_writer.py
swh/journal/tests/test_pytest_plugin.py
swh/journal/tests/test_serializers.py
swh/journal/tests/test_stream.py
swh/journal/writer/__init__.py
swh/journal/writer/inmemory.py
swh/journal/writer/interface.py
swh/journal/writer/kafka.py
swh/journal/writer/stream.py
swh_journal-2.0.0.dist-info/licenses/AUTHORS
swh_journal-2.0.0.dist-info/licenses/LICENSE
swh_journal-2.0.0.dist-info/METADATA
swh_journal-2.0.0.dist-info/WHEEL
swh_journal-2.0.0.dist-info/top_level.txt
swh_journal-2.0.0.dist-info/RECORD
